<?xml version="1.0" encoding="UTF-8"?>
<beans xmlns="http://www.springframework.org/schema/beans"
	xmlns:xsi="http://www.w3.org/2001/XMLSchema-instance"
	xsi:schemaLocation="http://www.springframework.org/schema/beans
		http://www.springframework.org/schema/beans/spring-beans.xsd">


	<bean id="ca35b_adc_output" class="gda.device.scannable.PVScannable">
		<property name="pvName" value="BL07B-EA-ENDST-02:I1:I" />
		<property name="deadband" value="0.001"/>
	</bean>
	
	<bean id="ca36b_adc_output" class="gda.device.scannable.PVScannable">
		<property name="pvName" value="BL07B-EA-ENDST-02:I2:I" />
		<property name="deadband" value="0.001"/>
	</bean>
	
</beans>