<?xml version="1.0" encoding="UTF-8"?>
<beans xmlns="http://www.springframework.org/schema/beans"
	xmlns:xsi="http://www.w3.org/2001/XMLSchema-instance"
	xsi:schemaLocation="http://www.springframework.org/schema/beans http://www.springframework.org/schema/beans/spring-beans.xsd">

	<bean id="andor_x_motor" class="gda.device.motor.DummyMotor">
		<property name="minPosition" value="-5.3" />
		<property name="maxPosition" value="5.4" />
		<property name="position" value="2.3" />
		<property name="speed" value="100" />
	 	<property name="unitString" value="mm"/>
	</bean>

	<bean id="andor_y_motor" class="gda.device.motor.DummyMotor">
		<property name="minPosition" value="-5.9" />
		<property name="maxPosition" value="5.3" />
		<property name="position" value="-5.7004" />
		<property name="speed" value="100" />
	 	<property name="unitString" value="mm"/>
	</bean>

	<bean id="andor_z_motor" class="gda.device.motor.DummyMotor">
		<property name="minPosition" value="200.0" />
		<property name="maxPosition" value="350.0" />
		<property name="position" value="249.87" />
		<property name="speed" value="100" />
	 	<property name="unitString" value="mm"/>
	</bean>

</beans>