<beans xmlns="http://www.springframework.org/schema/beans"
	xmlns:xsi="http://www.w3.org/2001/XMLSchema-instance" xmlns:util="http://www.springframework.org/schema/util"
	xmlns:tx="http://www.springframework.org/schema/tx" xmlns:aop="http://www.springframework.org/schema/aop"
	xmlns:corba="http://www.diamond.ac.uk/schema/gda/corba"
	xsi:schemaLocation="http://www.springframework.org/schema/beans http://www.springframework.org/schema/beans/spring-beans-2.5.xsd
		http://www.springframework.org/schema/util http://www.springframework.org/schema/util/spring-util-2.5.xsd
		http://www.springframework.org/schema/tx http://www.springframework.org/schema/tx/spring-tx-2.5.xsd
		http://www.springframework.org/schema/aop http://www.springframework.org/schema/aop/spring-aop-2.5.xsd
		http://www.diamond.ac.uk/schema/gda/corba http://www.diamond.ac.uk/schema/gda/corba/gda-corba-1.0.xsd">

	<bean id="sockpuppet" class="gda.data.fileregistrar.ClientFileAnnouncer" />

	<bean id="FileRegistrar" class="gda.data.fileregistrar.FileRegistrar">
			<property name="name" value="FileRegistrar" />
			<property name="directory" value="${gda.archiver.dropfiledir:/tmp/}" />
			<property name="clientFileAnnouncer" ref="sockpuppet" />
	</bean>

	<bean id="bssc_proc" class="uk.ac.gda.server.ncd.data.AutoProcessingRunner">
		<property name="scriptPath" value="${gda.bssc.processingscript}"/>
	</bean>

	<bean id="autoPostProcessing" class="uk.ac.gda.server.ncd.data.scan.MetaDataProcessingScanListener">
		<property name="detector" ref="ncddetectors"/>
		<property name="runner" ref="bssc_proc" />
		<property name="enabled" value="true"/>
	</bean>

	<bean id="twodscan" class="gda.data.scan.TwoDPlotListener">
		<property name="plotPanel" value="Plot 2D" />
	</bean>

	<bean id="scanListFileWriter" class="uk.ac.gda.server.ncd.data.scan.ScanListDataWriterExtender">
		<property name="filename" value="scanlist.csv" />
	</bean>

	<bean id="scan2terminal" class="uk.ac.gda.server.ncd.data.ScanInformationTerminalLogger">
		<property name="extractorList">
			<list>
				<bean class="uk.ac.gda.server.ncd.data.TfgSettingsExtractor" />
			</list>
		</property>
	</bean>

	<bean id="DefaultDataWriterFactory" class="gda.data.scan.datawriter.DefaultDataWriterFactory">
		<property name="name" value="DataWriterFactory" />
		<property name="dataWriterExtenders">
			<list>
				<ref bean="FileRegistrar" />
				<ref bean="scan2elog" />
				<ref bean="autoPostProcessing" />
				<ref bean="twodscan" />
				<ref bean="scanListFileWriter" />
				<ref bean="scan2terminal" />
			</list>
		</property>
	</bean>

	<bean
		class="org.springframework.beans.factory.config.MethodInvokingFactoryBean">
		<property name="staticMethod"
			value="gda.data.scan.datawriter.NexusDataWriter.setLocationmap" />
		<property name="arguments">
			<map>
				<entry key="energy">
					<bean class="gda.data.scan.datawriter.scannablewriter.SingleScannableWriter">
						<property name="paths"
							value="instrument:NXinstrument/monochromator:NXmonochromator/energy" />
						<property name="units" value="keV" />
					</bean>
				</entry>
				<entry key="idgap_mm">
					<bean class="gda.data.scan.datawriter.scannablewriter.SingleScannableWriter">
						<property name="paths"
							value="instrument:NXinstrument/insertion_device:NXinsertion_device/gap" />
						<property name="units" value="mm" />
					</bean>
				</entry>
				<entry key="s6_ysize">
					<bean class="gda.data.scan.datawriter.scannablewriter.SingleScannableWriter">
						<property name="paths"
							value="instrument:NXinstrument/monochromator:NXmonochromator/exit_slit_size" />
						<property name="units" value="mm" />
						<property name="prerequisiteScannableNames">
							<list>
								<value>energy</value>
								<value>pgm_cff</value>
								<value>pgm_linedensity</value>
							</list>
						</property>
					</bean>
				</entry>
				<entry key="s6_xsize">
					<bean class="gda.data.scan.datawriter.scannablewriter.SingleScannableWriter">
						<property name="paths"
							value="instrument:NXinstrument/monochromator:NXmonochromator/exit_slit_size_horizontal" />
						<property name="units" value="mm" />
						<property name="prerequisiteScannableNames">
							<list>
								<value>energy</value>
								<value>pgm_cff</value>
								<value>pgm_linedensity</value>
							</list>
						</property>
					</bean>
				</entry>
				<entry key="s2_ysize">
					<bean class="gda.data.scan.datawriter.scannablewriter.SingleScannableWriter">
						<property name="paths"
							value="instrument:NXinstrument/monochromator:NXmonochromator/s2_vertical_slit_size" />
						<property name="units" value="mm" />
					</bean>
				</entry>
				<entry key="s2_xsize">
					<bean class="gda.data.scan.datawriter.scannablewriter.SingleScannableWriter">
						<property name="paths"
							value="instrument:NXinstrument/monochromator:NXmonochromator/s2_horizontal_slit_size" />
						<property name="units" value="mm" />
					</bean>
				</entry>
				<entry key="pgm_linedensity">
					<bean class="gda.data.scan.datawriter.scannablewriter.SingleScannableWriter">
						<property name="paths"
							value="instrument:NXinstrument/monochromator:NXmonochromator/grating:NXgrating/line_density" />
						<property name="units" value="1/mm" />
					</bean>
				</entry>
				<entry key="bsscscannable">
					<bean class="gda.data.scan.datawriter.scannablewriter.SingleScannableWriter">
						<property name="paths">
							<list>
								<value>sample:NXsample/temperature</value>
								<value>instrument:NXinstrument/BSSC:NXobject/storage_temperature</value>
								<value>instrument:NXinstrument/BSSC:NXobject/detergent_level</value>
								<value>instrument:NXinstrument/BSSC:NXobject/water_level</value>
								<value>instrument:NXinstrument/BSSC:NXobject/waste_level</value>
							</list>
						</property>
						<property name="units">
							<list>
								<value>C</value>
								<value>C</value>
								<value>%</value>
								<value>%</value>
								<value>%</value>
							</list>
						</property>
					</bean>
				</entry>
				<entry key="sample_name">
					<bean class="gda.data.scan.datawriter.scannablewriter.SingleScannableWriter">
						<property name="paths" value="sample:NXsample/name" />
					</bean>
				</entry>
				<entry key="sample_environment">
					<bean class="gda.data.scan.datawriter.scannablewriter.SingleScannableWriter">
						<property name="paths" value="environment:NXenvironment/type" />
					</bean>
				</entry>
				<entry key="sample_type">
					<bean class="gda.data.scan.datawriter.scannablewriter.SingleScannableWriter">
						<property name="paths" value="sample:NXsample/type" />
					</bean>
				</entry>
				<entry key="sample_thickness">
					<bean class="gda.data.scan.datawriter.scannablewriter.SingleScannableWriter">
						<property name="paths" value="sample:NXsample/thickness" />
					</bean>
				</entry>
				<entry key="sample_concentration">
					<bean class="gda.data.scan.datawriter.scannablewriter.SingleScannableWriter">
						<property name="paths" value="sample:NXsample/concentration" />
						<property name="units" value="mg/ml"/>
					</bean>
				</entry>
				<entry key="sax">
					<bean class="gda.data.scan.datawriter.scannablewriter.SingleScannableWriter">
						<property name="paths"
							value="instrument:NXinstrument/manipulator:NXgoniometer/sax" />
						<property name="units" value="mm" />
					</bean>
				</entry>
				<entry key="say">
					<bean class="gda.data.scan.datawriter.scannablewriter.SingleScannableWriter">
						<property name="paths"
							value="instrument:NXinstrument/manipulator:NXgoniometer/say" />
						<property name="units" value="mm" />
					</bean>
				</entry>
				<entry key="saz">
					<bean class="gda.data.scan.datawriter.scannablewriter.SingleScannableWriter">
						<property name="paths"
							value="instrument:NXinstrument/manipulator:NXgoniometer/saz" />
						<property name="units" value="mm" />
					</bean>
				</entry>
				<entry key="experiment_definition">
                    <bean
                        class="gda.data.scan.datawriter.scannablewriter.SingleScannableWriter">
                        <property name="paths">
                            <list>
                                <value>experiment_definition:NXparameters/samples</value>
                                <value>experiment_definition:NXparameters/index</value>
                                <value>experiment_definition:NXparameters/identifier</value>
                            </list>
                        </property>
                        <!-- <property name="paths" value="experiment_definition:NXcollection/samples" /> -->
                        <property name="prerequisiteScannableNames">
                            <list />
                        </property>
                    </bean>
                </entry>
			</map>
		</property>
	</bean>
</beans>
