<beans xmlns="http://www.springframework.org/schema/beans"
       xmlns:xsi="http://www.w3.org/2001/XMLSchema-instance"
       xsi:schemaLocation="http://www.springframework.org/schema/beans
           http://www.springframework.org/schema/beans/spring-beans.xsd">

<!-- 	<bean id="newport_1_motor" class="gda.device.motor.EpicsMotor">
		<property name="pvName" value="BL13I-MO-CAM-04:FOCUS"/>
		<property name="configureAtStartup" value="${use.newport}"/>
	</bean> -->
	<bean id="newport_2_motor" class="gda.device.motor.EpicsMotor">
		<property name="pvName" value="BL13I-MO-GNRIC-01:NEWPORTMFA:2"/>
		<property name="configureAtStartup" value="${use.newport}"/>
	</bean>
	<bean id="newport_3_motor" class="gda.device.motor.EpicsMotor">
		<property name="pvName" value="BL13I-MO-GNRIC-01:NEWPORTMFA:3"/>
		<property name="configureAtStartup" value="${use.newport}"/>
	</bean>


</beans>
