<?xml version="1.0" encoding="UTF-8"?>
<beans xmlns="http://www.springframework.org/schema/beans"
	xmlns:xsi="http://www.w3.org/2001/XMLSchema-instance"
	xsi:schemaLocation="http://www.springframework.org/schema/beans http://www.springframework.org/schema/beans/spring-beans.xsd">

	
	<bean id="xrcremote" class="gda.device.enumpositioner.DummyEnumPositioner"/>
	<bean id="xrcstatus" class="gda.device.enumpositioner.DummyEnumPositioner"/>
	<bean id="xrcfc" class="gda.device.monitor.DummyEpicsMonitor"/>
	<bean id="xrcfv" class="gda.device.monitor.DummyEpicsMonitor"/>
	<bean id="xrcanodep" class="gda.device.monitor.DummyEpicsMonitor"/>
	<bean id="xrcanode" class="gda.device.enumpositioner.DummyEnumPositioner"/>
	<bean id="xrcanodev" class="gda.device.scannable.DummyScannable"/>
	<bean id="xrcec" class="gda.device.scannable.DummyScannable"/>

</beans>