<beans xmlns="http://www.springframework.org/schema/beans"
	xmlns:xsi="http://www.w3.org/2001/XMLSchema-instance"
	xsi:schemaLocation="http://www.springframework.org/schema/beans
           http://www.springframework.org/schema/beans/spring-beans-2.5.xsd">


<!-- SR08I-MO-SERVC-01:BLGAPMTR -->
	
	<bean id="opticsShutter" class="gda.device.enumpositioner.EpicsPneumaticCallback">
		<property name="local" value="false"/>
		<property name="pvBase" value="FE08I-PS-SHTR-02"/>
	</bean>
	
	<bean id="d1" class="gda.device.monitor.EpicsMonitor">
		<property name="pvName" value="BL08I-DI-PHDGN-01:CAM1:STAT:Total_RBV"/>
		<property name="local" value="true"/>
		 <property name="poll" value="true" />
	</bean>
	
	<bean id="d2" class="gda.device.monitor.EpicsMonitor">
		<property name="pvName" value="BL08I-DI-PHDGN-02:CAM1:STAT:Total_RBV"/>
		<property name="local" value="true"/>
		 <property name="poll" value="true" />
	</bean>
	
	<bean id="d3" class="gda.device.monitor.EpicsMonitor">
		<property name="pvName" value="BL08I-DI-PHDGN-03:CAM1:STAT:Total_RBV"/>
		<property name="local" value="true"/>
		 <property name="poll" value="true" />
	</bean>
	
	<bean id="d4" class="gda.device.monitor.EpicsMonitor">
		<property name="pvName" value="BL08I-DI-PHDGN-04:CAM1:STAT:Total_RBV"/>
		<property name="local" value="true"/>
		 <property name="poll" value="true" />
	</bean>
		
	<bean id="d5" class="gda.device.monitor.EpicsMonitor">
		<property name="pvName" value="BL08I-DI-PHDGN-05:CAM1:STAT:Total_RBV"/>
		<property name="local" value="true"/>
		 <property name="poll" value="true" />
	</bean>
	
	<bean id="d6" class="gda.device.monitor.EpicsMonitor">
		<property name="pvName" value="BL08I-DI-PHDGN-06:CAM1:STAT:Total_RBV"/>
		<property name="local" value="true"/>
		 <property name="poll" value="true" />
	</bean> 
	
	<bean id="shutter1" class="gda.device.enumpositioner.EpicsPneumaticCallback">
		<property name="local" value="false"/>
		<property name="pvBase" value="BL08I-PS-SHTR-01"/>
	</bean>
	
</beans> 
