<?xml version="1.0" encoding="UTF-8"?>
<beans xmlns="http://www.springframework.org/schema/beans"
	xmlns:xsi="http://www.w3.org/2001/XMLSchema-instance"
	xsi:schemaLocation="http://www.springframework.org/schema/beans
	http://www.springframework.org/schema/beans/spring-beans.xsd">

	<description>
		The ScannableMotors representing an XY stage to be used for mapping scans
	</description>

	<bean id="T1X" class="gda.device.scannable.ScannableMotor">
		<property name="motor" ref="T1X_motor" />
	</bean>

	<bean id="T1Y" class="gda.device.scannable.ScannableMotor">
		<property name="motor" ref="T1Y_motor" />
	</bean>

	<bean id="T1ZC" class="gda.device.scannable.ScannableMotor">
		<property name="motor" ref="T1ZC_motor" />
	</bean>

	<bean id="t1" class="gda.device.scannable.scannablegroup.ScannableGroup">
		<property name="groupMembers">
			<list>
				<ref bean="T1X" />
				<ref bean="T1Y" />
				<ref bean="T1ZC" />
			</list>
		</property>
	</bean>

</beans>
