<?xml version="1.0" encoding="UTF-8"?>
<VortexParameters>
    <detectorName>xmapMca</detectorName>
    <tfgName>tfg</tfgName>
    <countType>Static</countType>
    <collectionTime>1000.0</collectionTime>
    <DetectorElement>
        <name>Element0</name>
        <number>1</number>
        <ROI>
            <name>S_Ka</name>
            <windowStart>216</windowStart>
            <windowEnd>246</windowEnd>
            <counts>67856</counts>
        </ROI>
        <gain>2.0</gain>
        <peakingTime>1.04</peakingTime>
        <offset>-21.0</offset>
        <excluded>false</excluded>
    </DetectorElement>
    <DetectorElement>
        <name>Element1</name>
        <number>1</number>
        <ROI>
            <name>S_Ka</name>
            <windowStart>216</windowStart>
            <windowEnd>246</windowEnd>
            <counts>69890</counts>
        </ROI>
        <gain>2.0</gain>
        <peakingTime>1.04</peakingTime>
        <offset>-21.0</offset>
        <excluded>false</excluded>
    </DetectorElement>
    <DetectorElement>
        <name>Element2</name>
        <number>1</number>
        <ROI>
            <name>S_Ka</name>
            <windowStart>216</windowStart>
            <windowEnd>246</windowEnd>
            <counts>58614</counts>
        </ROI>
        <gain>2.0</gain>
        <peakingTime>1.04</peakingTime>
        <offset>-21.0</offset>
        <excluded>false</excluded>
    </DetectorElement>
    <DetectorElement>
        <name>Element3</name>
        <number>1</number>
        <ROI>
            <name>S_Ka</name>
            <windowStart>216</windowStart>
            <windowEnd>246</windowEnd>
            <counts>65818</counts>
        </ROI>
        <gain>2.0</gain>
        <peakingTime>1.04</peakingTime>
        <offset>-21.0</offset>
        <excluded>false</excluded>
    </DetectorElement>
    <deadTime>-0.01</deadTime>
    <saveRawSpectrum>false</saveRawSpectrum>
</VortexParameters>
