<?xml version="1.0" encoding="UTF-8"?>
<!--ObjectFactory xmlns:xsi="http://www.w3.org/2001/XMLSchema-instance"
    xsi:noNamespaceSchemaLocation="/home/fy65/workspace/gda/src/gda/configuration/object/schema/GDASchema.xsd"-->
<ObjectFactory>
   <name>i22</name>
     
    <!-- ************************ -->
    <!-- *** Optical Elements *** -->
    <!-- ************************ -->
   
    <!-- Insertion Device -->
    <GenericOE>
        <name>ID</name>
            <local>true</local>
        <LinearPositioner>
            <local>true</local>
            <name>idgap_positioner</name>
            <motorName>idgap_motor</motorName>
            <stepsPerUnit>1</stepsPerUnit>
            <softLimitLow>-100</softLimitLow>
            <softLimitHigh>100</softLimitHigh>
            <poll>false</poll>
        </LinearPositioner>
        <EpicsAxisLinearDOF>
            <local>true</local>
            <name>idgap_mm</name>
            <protectionLevel>2</protectionLevel>
            <acceptableUnit>mm</acceptableUnit>
            <moveableName>idgap_positioner</moveableName>
        </EpicsAxisLinearDOF>
    </GenericOE>
    <!-- FE aperture elements-->
    <GenericOE>
        <name>FEAPTR</name>
            <local>true</local>
        <LinearPositioner>
            <local>true</local>
            <name>feaptr_x_positioner</name>
            <motorName>feaptr_x_motor</motorName>
            <stepsPerUnit>1</stepsPerUnit>
            <softLimitLow>-100</softLimitLow>
            <softLimitHigh>100</softLimitHigh>
            <poll>false</poll>
        </LinearPositioner>
        <LinearPositioner>
            <local>true</local>
            <name>feaptr_y_positioner</name>
            <motorName>feaptr_y_motor</motorName>
            <stepsPerUnit>1</stepsPerUnit>
            <softLimitLow>-100</softLimitLow>
            <softLimitHigh>100</softLimitHigh>
            <poll>false</poll>
        </LinearPositioner>
        <EpicsAxisLinearDOF>
            <local>true</local>
            <name>xaptr</name>
            <protectionLevel>3</protectionLevel>
            <acceptableUnit>mm</acceptableUnit>
            <moveableName>feaptr_x_positioner</moveableName>
        </EpicsAxisLinearDOF>
        <EpicsAxisLinearDOF>
            <local>true</local>
            <name>yaptr</name>
            <protectionLevel>3</protectionLevel>
            <acceptableUnit>mm</acceptableUnit>
            <moveableName>feaptr_y_positioner</moveableName>
        </EpicsAxisLinearDOF>
    </GenericOE>

    <GenericOE>
        <name>FS</name>
            <local>true</local>
        <LinearPositioner>
            <local>true</local>
            <name>fastshuttermotor_positioner</name>
            <motorName>fastshuttermotor_motor</motorName>
            <stepsPerUnit>1</stepsPerUnit>
            <softLimitLow>-100</softLimitLow>
            <softLimitHigh>100</softLimitHigh>
            <poll>false</poll>
        </LinearPositioner>
        <EpicsAxisLinearDOF>
            <local>true</local>
            <name>fsmotor</name>
            <protectionLevel>3</protectionLevel>
            <acceptableUnit>mm</acceptableUnit>
            <moveableName>fastshuttermotor_positioner</moveableName>
        </EpicsAxisLinearDOF>
    </GenericOE>

    <!-- Primary Slits / S1 Optical Elements -->
    <GenericOE>
        <name>S1</name>
            <local>true</local>
        <LinearPositioner>
            <local>true</local>
            <name>s1xpos_positioner</name>
            <motorName>s1xpos_motor</motorName>
            <stepsPerUnit>1</stepsPerUnit>
            <softLimitLow>-100</softLimitLow>
            <softLimitHigh>100</softLimitHigh>
            <poll>false</poll>
        </LinearPositioner>
        <LinearPositioner>
            <local>true</local>
            <name>s1xgap_positioner</name>
            <motorName>s1xgap_motor</motorName>
            <stepsPerUnit>1</stepsPerUnit>
            <softLimitLow>-100</softLimitLow>
            <softLimitHigh>100</softLimitHigh>
            <poll>false</poll>
        </LinearPositioner>
        <LinearPositioner>
            <local>true</local>
            <name>s1ypos_positioner</name>
            <motorName>s1ypos_motor</motorName>
            <stepsPerUnit>1</stepsPerUnit>
            <softLimitLow>-100</softLimitLow>
            <softLimitHigh>100</softLimitHigh>
            <poll>false</poll>
        </LinearPositioner>
        <LinearPositioner>
            <local>true</local>
            <name>s1ygap_positioner</name>
            <motorName>s1ygap_motor</motorName>
            <stepsPerUnit>1</stepsPerUnit>
            <softLimitLow>-100</softLimitLow>
            <softLimitHigh>100</softLimitHigh>
            <poll>false</poll>
        </LinearPositioner>
        <LinearPositioner>
            <local>true</local>
            <name>s1xplus_positioner</name>
            <motorName>s1xplus_motor</motorName>
            <stepsPerUnit>1</stepsPerUnit>
            <softLimitLow>-100</softLimitLow>
            <softLimitHigh>100</softLimitHigh>
            <poll>false</poll>
        </LinearPositioner>
        <LinearPositioner>
            <local>true</local>
            <name>s1xminus_positioner</name>
            <motorName>s1xminus_motor</motorName>
            <stepsPerUnit>1</stepsPerUnit>
            <softLimitLow>-100</softLimitLow>
            <softLimitHigh>100</softLimitHigh>
            <poll>false</poll>
        </LinearPositioner>
        <LinearPositioner>
            <local>true</local>
            <name>s1yplus_positioner</name>
            <motorName>s1yplus_motor</motorName>
            <stepsPerUnit>1</stepsPerUnit>
            <softLimitLow>-100</softLimitLow>
            <softLimitHigh>100</softLimitHigh>
            <poll>false</poll>
        </LinearPositioner>
        <LinearPositioner>
            <local>true</local>
            <name>s1yminus_positioner</name>
            <motorName>s1yminus_motor</motorName>
            <stepsPerUnit>1</stepsPerUnit>
            <softLimitLow>-100</softLimitLow>
            <softLimitHigh>100</softLimitHigh>
            <poll>false</poll>
        </LinearPositioner>
        
        <EpicsAxisLinearDOF>
            <local>true</local>
            <name>s1xcentre</name>
            <protectionLevel>2</protectionLevel>
            <acceptableUnit>mm</acceptableUnit>
            <moveableName>s1xpos_positioner</moveableName>
        </EpicsAxisLinearDOF>
        <EpicsAxisLinearDOF>
            <local>true</local>
            <name>s1xgap</name>
            <protectionLevel>2</protectionLevel>
            <acceptableUnit>mm</acceptableUnit>
            <moveableName>s1xgap_positioner</moveableName>
        </EpicsAxisLinearDOF>
        <EpicsAxisLinearDOF>
            <local>true</local>
            <name>s1ycentre</name>
            <protectionLevel>2</protectionLevel>
            <acceptableUnit>mm</acceptableUnit>
            <moveableName>s1ypos_positioner</moveableName>
        </EpicsAxisLinearDOF>
        <EpicsAxisLinearDOF>
            <local>true</local>
            <name>s1ygap</name>
            <protectionLevel>2</protectionLevel>
            <acceptableUnit>mm</acceptableUnit>
            <moveableName>s1ygap_positioner</moveableName>
        </EpicsAxisLinearDOF>
        <EpicsAxisLinearDOF>
            <local>true</local>
            <name>s1xplus</name>
            <protectionLevel>2</protectionLevel>
            <acceptableUnit>mm</acceptableUnit>
            <moveableName>s1xplus_positioner</moveableName>
        </EpicsAxisLinearDOF>
        <EpicsAxisLinearDOF>
            <local>true</local>
            <name>s1xminus</name>
            <protectionLevel>2</protectionLevel>
            <acceptableUnit>mm</acceptableUnit>
            <moveableName>s1xminus_positioner</moveableName>
        </EpicsAxisLinearDOF>
        <EpicsAxisLinearDOF>
            <local>true</local>
            <name>s1yplus</name>
            <protectionLevel>2</protectionLevel>
            <acceptableUnit>mm</acceptableUnit>
            <moveableName>s1yplus_positioner</moveableName>
        </EpicsAxisLinearDOF>
        <EpicsAxisLinearDOF>
            <local>true</local>
            <name>s1yminus</name>
            <protectionLevel>2</protectionLevel>
            <acceptableUnit>mm</acceptableUnit>
            <moveableName>s1yminus_positioner</moveableName>
        </EpicsAxisLinearDOF>
    </GenericOE>
    <!-- D1 -->
    <GenericOE>
        <name>D1</name>
            <local>true</local>
        <LinearPositioner>
            <local>true</local>
            <name>d1motor_positioner</name>
            <motorName>d1motor_motor</motorName>
            <stepsPerUnit>1</stepsPerUnit>
            <softLimitLow>-100</softLimitLow>
            <softLimitHigh>100</softLimitHigh>
            <poll>false</poll>
        </LinearPositioner>
        <EpicsAxisLinearDOF>
            <local>true</local>
            <name>d1motor</name>
            <protectionLevel>2</protectionLevel>
            <acceptableUnit>mm</acceptableUnit>
            <moveableName>d1motor_positioner</moveableName>
        </EpicsAxisLinearDOF>
    </GenericOE>
    <!-- D2 -->
    <GenericOE>
        <name>D2</name>
            <local>true</local>
        <LinearPositioner>
            <local>true</local>
            <name>d2motor_positioner</name>
            <motorName>d2motor_motor</motorName>
            <stepsPerUnit>1</stepsPerUnit>
            <softLimitLow>-100</softLimitLow>
            <softLimitHigh>100</softLimitHigh>
            <poll>false</poll>
        </LinearPositioner>
        <EpicsAxisLinearDOF>
            <local>true</local>
            <name>d2motor</name>
            <protectionLevel>2</protectionLevel>
            <acceptableUnit>mm</acceptableUnit>
            <moveableName>d2motor_positioner</moveableName>
        </EpicsAxisLinearDOF>
    </GenericOE>   
        
    <!-- Secondary Slits / S2 Optical Element -->
    <GenericOE>
        <name>S2</name>
            <local>true</local>
        <LinearPositioner>
            <local>true</local>
            <name>s2xpos_positioner</name>
            <motorName>s2xpos_motor</motorName>
            <stepsPerUnit>1</stepsPerUnit>
            <softLimitLow>-100</softLimitLow>
            <softLimitHigh>100</softLimitHigh>
            <poll>false</poll>
        </LinearPositioner>
        <LinearPositioner>
            <local>true</local>
            <name>s2xgap_positioner</name>
            <motorName>s2xgap_motor</motorName>
            <stepsPerUnit>1</stepsPerUnit>
            <softLimitLow>-100</softLimitLow>
            <softLimitHigh>100</softLimitHigh>
            <poll>false</poll>
        </LinearPositioner>
        <LinearPositioner>
            <local>true</local>
            <name>s2ypos_positioner</name>
            <motorName>s2ypos_motor</motorName>
            <stepsPerUnit>1</stepsPerUnit>
            <softLimitLow>-100</softLimitLow>
            <softLimitHigh>100</softLimitHigh>
            <poll>false</poll>
        </LinearPositioner>
        <LinearPositioner>
            <local>true</local>
            <name>s2ygap_positioner</name>
            <motorName>s2ygap_motor</motorName>
            <stepsPerUnit>1</stepsPerUnit>
            <softLimitLow>-100</softLimitLow>
            <softLimitHigh>100</softLimitHigh>
            <poll>false</poll>
        </LinearPositioner>
        <LinearPositioner>
            <local>true</local>
            <name>s2xplus_positioner</name>
            <motorName>s2xplus_motor</motorName>
            <stepsPerUnit>1</stepsPerUnit>
            <softLimitLow>-100</softLimitLow>
            <softLimitHigh>100</softLimitHigh>
            <poll>false</poll>
        </LinearPositioner>
        <LinearPositioner>
            <local>true</local>
            <name>s2xminus_positioner</name>
            <motorName>s2xminus_motor</motorName>
            <stepsPerUnit>1</stepsPerUnit>
            <softLimitLow>-100</softLimitLow>
            <softLimitHigh>100</softLimitHigh>
            <poll>false</poll>
        </LinearPositioner>
        <LinearPositioner>
            <local>true</local>
            <name>s2yplus_positioner</name>
            <motorName>s2yplus_motor</motorName>
            <stepsPerUnit>1</stepsPerUnit>
            <softLimitLow>-100</softLimitLow>
            <softLimitHigh>100</softLimitHigh>
            <poll>false</poll>
        </LinearPositioner>
        <LinearPositioner>
            <local>true</local>
            <name>s2yminus_positioner</name>
            <motorName>s2yminus_motor</motorName>
            <stepsPerUnit>1</stepsPerUnit>
            <softLimitLow>-100</softLimitLow>
            <softLimitHigh>100</softLimitHigh>
            <poll>false</poll>
        </LinearPositioner>
        
        <EpicsAxisLinearDOF>
            <local>true</local>
            <name>s2xcentre</name>
            <protectionLevel>2</protectionLevel>
            <acceptableUnit>mm</acceptableUnit>
            <moveableName>s2xpos_positioner</moveableName>
        </EpicsAxisLinearDOF>
        <EpicsAxisLinearDOF>
            <local>true</local>
            <name>s2xgap</name>
            <protectionLevel>2</protectionLevel>
            <acceptableUnit>mm</acceptableUnit>
            <moveableName>s2xgap_positioner</moveableName>
        </EpicsAxisLinearDOF>
        <EpicsAxisLinearDOF>
            <local>true</local>
            <name>s2ycentre</name>
            <protectionLevel>2</protectionLevel>
            <acceptableUnit>mm</acceptableUnit>
            <moveableName>s2ypos_positioner</moveableName>
        </EpicsAxisLinearDOF>
        <EpicsAxisLinearDOF>
            <local>true</local>
            <name>s2ygap</name>
            <protectionLevel>2</protectionLevel>
            <acceptableUnit>mm</acceptableUnit>
            <moveableName>s2ygap_positioner</moveableName>
        </EpicsAxisLinearDOF>
        <EpicsAxisLinearDOF>
            <local>true</local>
            <name>s2xplus</name>
            <protectionLevel>2</protectionLevel>
            <acceptableUnit>mm</acceptableUnit>
            <moveableName>s2xplus_positioner</moveableName>
        </EpicsAxisLinearDOF>
        <EpicsAxisLinearDOF>
            <local>true</local>
            <name>s2xminus</name>
            <protectionLevel>2</protectionLevel>
            <acceptableUnit>mm</acceptableUnit>
            <moveableName>s2xminus_positioner</moveableName>
        </EpicsAxisLinearDOF>
        <EpicsAxisLinearDOF>
            <local>true</local>
            <name>s2yplus</name>
            <protectionLevel>2</protectionLevel>
            <acceptableUnit>mm</acceptableUnit>
            <moveableName>s2yplus_positioner</moveableName>
        </EpicsAxisLinearDOF>
        <EpicsAxisLinearDOF>
            <local>true</local>
            <name>s2yminus</name>
            <protectionLevel>2</protectionLevel>
            <acceptableUnit>mm</acceptableUnit>
            <moveableName>s2yminus_positioner</moveableName>
        </EpicsAxisLinearDOF>
    </GenericOE>    
    
    <!-- D3 -->
    <GenericOE>
        <name>D3</name>
            <local>true</local>
        <LinearPositioner>
            <local>true</local>
            <name>d3motor_positioner</name>
            <motorName>d3motor_motor</motorName>
            <stepsPerUnit>1</stepsPerUnit>
            <softLimitLow>-100</softLimitLow>
            <softLimitHigh>100</softLimitHigh>
            <poll>false</poll>
        </LinearPositioner>
        <EpicsAxisLinearDOF>
            <local>true</local>
            <name>d3motor</name>
            <protectionLevel>2</protectionLevel>
            <acceptableUnit>mm</acceptableUnit>
            <moveableName>d3motor_positioner</moveableName>
        </EpicsAxisLinearDOF>
    </GenericOE>
    
    <!-- KB Mirror -->
    <GenericOE>
        <name>KBM</name>
            <local>true</local>
        <LinearPositioner>
            <local>true</local>
            <name>vfmx_positioner</name>
            <motorName>vfmx_motor</motorName>
            <stepsPerUnit>1</stepsPerUnit>
            <softLimitLow>-100</softLimitLow>
            <softLimitHigh>100</softLimitHigh>
            <poll>false</poll>
        </LinearPositioner>
        <LinearPositioner>
            <local>true</local>
            <name>vfmy_positioner</name>
            <motorName>vfmy_motor</motorName>
            <stepsPerUnit>1</stepsPerUnit>
            <softLimitLow>-100</softLimitLow>
            <softLimitHigh>100</softLimitHigh>
            <poll>false</poll>
        </LinearPositioner>
        <AngularPositioner>
            <local>true</local>
            <name>vfmpitch_positioner</name>
            <motorName>vfmpitch_motor</motorName>
            <stepsPerUnit>1</stepsPerUnit>
            <softLimitLow>-100</softLimitLow>
            <softLimitHigh>100</softLimitHigh>
            <poll>false</poll>
        </AngularPositioner>
        <AngularPositioner>
            <local>true</local>
            <name>vfmroll_positioner</name>
            <motorName>vfmroll_motor</motorName>
            <stepsPerUnit>1</stepsPerUnit>
            <softLimitLow>-100</softLimitLow>
            <softLimitHigh>100</softLimitHigh>
            <poll>false</poll>
        </AngularPositioner>
        <AngularPositioner>
            <local>true</local>
            <name>vfmyaw_positioner</name>
            <motorName>vfmyaw_motor</motorName>
            <stepsPerUnit>1</stepsPerUnit>
            <softLimitLow>-100</softLimitLow>
            <softLimitHigh>100</softLimitHigh>
            <poll>false</poll>
        </AngularPositioner>
        <LinearPositioner>
            <local>true</local>
            <name>hfmx_positioner</name>
            <motorName>hfmx_motor</motorName>
            <stepsPerUnit>1</stepsPerUnit>
            <softLimitLow>-100</softLimitLow>
            <softLimitHigh>100</softLimitHigh>
            <poll>false</poll>
        </LinearPositioner>
        <LinearPositioner>
            <local>true</local>
            <name>hfmy_positioner</name>
            <motorName>hfmy_motor</motorName>
            <stepsPerUnit>1</stepsPerUnit>
            <softLimitLow>-100</softLimitLow>
            <softLimitHigh>100</softLimitHigh>
            <poll>false</poll>
        </LinearPositioner>
        <AngularPositioner>
            <local>true</local>
            <name>hfmpitch_positioner</name>
            <motorName>hfmpitch_motor</motorName>
            <stepsPerUnit>1</stepsPerUnit>
            <softLimitLow>-100</softLimitLow>
            <softLimitHigh>100</softLimitHigh>
            <poll>false</poll>
        </AngularPositioner>
        <AngularPositioner>
            <local>true</local>
            <name>hfmroll_positioner</name>
            <motorName>hfmroll_motor</motorName>
            <stepsPerUnit>1</stepsPerUnit>
            <softLimitLow>-100</softLimitLow>
            <softLimitHigh>100</softLimitHigh>
            <poll>false</poll>
        </AngularPositioner>
        <AngularPositioner>
            <local>true</local>
            <name>hfmyaw_positioner</name>
            <motorName>hfmyaw_motor</motorName>
            <stepsPerUnit>1</stepsPerUnit>
            <softLimitLow>-100</softLimitLow>
            <softLimitHigh>100</softLimitHigh>
            <poll>false</poll>
        </AngularPositioner>
        
        <LinearPositioner>
            <local>true</local>
            <name>vfmx1_positioner</name>
            <motorName>vfmx1_motor</motorName>
            <stepsPerUnit>1</stepsPerUnit>
            <softLimitLow>-100</softLimitLow>
            <softLimitHigh>100</softLimitHigh>
            <poll>false</poll>
        </LinearPositioner>
        <LinearPositioner>
            <local>true</local>
            <name>vfmx2_positioner</name>
            <motorName>vfmx2_motor</motorName>
            <stepsPerUnit>1</stepsPerUnit>
            <softLimitLow>-100</softLimitLow>
            <softLimitHigh>100</softLimitHigh>
            <poll>false</poll>
        </LinearPositioner>
        <LinearPositioner>
            <local>true</local>
            <name>vfmy1_positioner</name>
            <motorName>vfmy1_motor</motorName>
            <stepsPerUnit>1</stepsPerUnit>
            <softLimitLow>-100</softLimitLow>
            <softLimitHigh>100</softLimitHigh>
            <poll>false</poll>
        </LinearPositioner>
        <LinearPositioner>
            <local>true</local>
            <name>vfmy2_positioner</name>
            <motorName>vfmy2_motor</motorName>
            <stepsPerUnit>1</stepsPerUnit>
            <softLimitLow>-100</softLimitLow>
            <softLimitHigh>100</softLimitHigh>
            <poll>false</poll>
        </LinearPositioner>
        <LinearPositioner>
            <local>true</local>
            <name>vfmy3_positioner</name>
            <motorName>vfmy3_motor</motorName>
            <stepsPerUnit>1</stepsPerUnit>
            <softLimitLow>-100</softLimitLow>
            <softLimitHigh>100</softLimitHigh>
            <poll>false</poll>
        </LinearPositioner>
        <LinearPositioner>
            <local>true</local>
            <name>hfmx1_positioner</name>
            <motorName>hfmx1_motor</motorName>
            <stepsPerUnit>1</stepsPerUnit>
            <softLimitLow>-100</softLimitLow>
            <softLimitHigh>100</softLimitHigh>
            <poll>false</poll>
        </LinearPositioner>
        <LinearPositioner>
            <local>true</local>
            <name>hfmx2_positioner</name>
            <motorName>hfmx2_motor</motorName>
            <stepsPerUnit>1</stepsPerUnit>
            <softLimitLow>-100</softLimitLow>
            <softLimitHigh>100</softLimitHigh>
            <poll>false</poll>
        </LinearPositioner>
        <LinearPositioner>
            <local>true</local>
            <name>hfmy1_positioner</name>
            <motorName>hfmy1_motor</motorName>
            <stepsPerUnit>1</stepsPerUnit>
            <softLimitLow>-100</softLimitLow>
            <softLimitHigh>100</softLimitHigh>
            <poll>false</poll>
        </LinearPositioner>
        <LinearPositioner>
            <local>true</local>
            <name>hfmy2_positioner</name>
            <motorName>hfmy2_motor</motorName>
            <stepsPerUnit>1</stepsPerUnit>
            <softLimitLow>-100</softLimitLow>
            <softLimitHigh>100</softLimitHigh>
            <poll>false</poll>
        </LinearPositioner>
        <LinearPositioner>
            <local>true</local>
            <name>hfmy3_positioner</name>
            <motorName>hfmy3_motor</motorName>
            <stepsPerUnit>1</stepsPerUnit>
            <softLimitLow>-100</softLimitLow>
            <softLimitHigh>100</softLimitHigh>
            <poll>false</poll>
        </LinearPositioner>
        <LinearPositioner>
            <local>true</local>
            <name>vfmtip_positioner</name>
            <motorName>vfmtip_motor</motorName>
            <stepsPerUnit>1</stepsPerUnit>
            <softLimitLow>-100</softLimitLow>
            <softLimitHigh>100</softLimitHigh>
            <poll>false</poll>
        </LinearPositioner>
        <LinearPositioner>
            <local>true</local>
            <name>vfmy2y3_positioner</name>
            <motorName>vfmy2y3_motor</motorName>
            <stepsPerUnit>1</stepsPerUnit>
            <softLimitLow>-100</softLimitLow>
            <softLimitHigh>100</softLimitHigh>
            <poll>false</poll>
        </LinearPositioner>
        
        <EpicsAxisLinearDOF>
            <local>true</local>
            <name>vfmx</name>
            <protectionLevel>3</protectionLevel>
            <acceptableUnit>mm</acceptableUnit>
            <moveableName>vfmx_positioner</moveableName>
        </EpicsAxisLinearDOF>
        <EpicsAxisLinearDOF>
            <local>true</local>
            <name>vfmy</name>
            <protectionLevel>3</protectionLevel>
            <acceptableUnit>mm</acceptableUnit>
            <moveableName>vfmy_positioner</moveableName>
        </EpicsAxisLinearDOF>
        <EpicsAxisAngularDOF>
            <local>true</local>
            <name>vfmpitch</name>
            <protectionLevel>3</protectionLevel>
            <acceptableUnit>Deg</acceptableUnit>
            <moveableName>vfmpitch_positioner</moveableName>
        </EpicsAxisAngularDOF>
        <EpicsAxisAngularDOF>
            <local>true</local>
            <name>vfmroll</name>
            <protectionLevel>3</protectionLevel>
            <acceptableUnit>Deg</acceptableUnit>
            <moveableName>vfmroll_positioner</moveableName>
        </EpicsAxisAngularDOF>
        <EpicsAxisAngularDOF>
            <local>true</local>
            <name>vfmyaw</name>
            <protectionLevel>3</protectionLevel>
            <acceptableUnit>Deg</acceptableUnit>
            <moveableName>vfmyaw_positioner</moveableName>
        </EpicsAxisAngularDOF>
        
        <EpicsAxisLinearDOF>
            <local>true</local>
            <name>hfmx</name>
            <protectionLevel>3</protectionLevel>
            <acceptableUnit>mm</acceptableUnit>
            <moveableName>hfmx_positioner</moveableName>
        </EpicsAxisLinearDOF>
        <EpicsAxisLinearDOF>
            <local>true</local>
            <name>hfmy</name>
            <protectionLevel>3</protectionLevel>
            <acceptableUnit>mm</acceptableUnit>
            <moveableName>hfmy_positioner</moveableName>
        </EpicsAxisLinearDOF>
        <EpicsAxisAngularDOF>
            <local>true</local>
            <name>hfmpitch</name>
            <protectionLevel>3</protectionLevel>
            <acceptableUnit>Deg</acceptableUnit>
            <moveableName>hfmpitch_positioner</moveableName>
        </EpicsAxisAngularDOF>
        <EpicsAxisAngularDOF>
            <local>true</local>
            <name>hfmroll</name>
            <protectionLevel>3</protectionLevel>
            <acceptableUnit>Deg</acceptableUnit>
            <moveableName>hfmroll_positioner</moveableName>
        </EpicsAxisAngularDOF>
        <EpicsAxisAngularDOF>
            <local>true</local>
            <name>hfmyaw</name>
            <protectionLevel>3</protectionLevel>
            <acceptableUnit>Deg</acceptableUnit>
            <moveableName>hfmyaw_positioner</moveableName>
        </EpicsAxisAngularDOF>       
        
        <EpicsAxisLinearDOF>
            <local>true</local>
            <name>vfmx1</name>
            <protectionLevel>3</protectionLevel>
            <acceptableUnit>mm</acceptableUnit>
            <moveableName>vfmx1_positioner</moveableName>
        </EpicsAxisLinearDOF>
        <EpicsAxisLinearDOF>
            <local>true</local>
            <name>vfmx2</name>
            <protectionLevel>3</protectionLevel>
            <acceptableUnit>mm</acceptableUnit>
            <moveableName>vfmx2_positioner</moveableName>
        </EpicsAxisLinearDOF>
        <EpicsAxisLinearDOF>
            <local>true</local>
            <name>vfmy1</name>
            <protectionLevel>3</protectionLevel>
            <acceptableUnit>mm</acceptableUnit>
            <moveableName>vfmy1_positioner</moveableName>
            </EpicsAxisLinearDOF>
        <EpicsAxisLinearDOF>
            <local>true</local>
            <name>vfmy2</name>
            <protectionLevel>3</protectionLevel>
            <acceptableUnit>mm</acceptableUnit>
            <moveableName>vfmy2_positioner</moveableName>
            </EpicsAxisLinearDOF>
        <EpicsAxisLinearDOF>
            <local>true</local>
            <name>vfmy3</name>
            <protectionLevel>3</protectionLevel>
            <acceptableUnit>mm</acceptableUnit>
            <moveableName>vfmy3_positioner</moveableName>
            </EpicsAxisLinearDOF>
        
        <EpicsAxisLinearDOF>
            <local>true</local>
            <name>hfmx1</name>
            <protectionLevel>3</protectionLevel>
            <acceptableUnit>mm</acceptableUnit>
            <moveableName>hfmx1_positioner</moveableName>
        </EpicsAxisLinearDOF>
        <EpicsAxisLinearDOF>
            <local>true</local>
            <name>hfmx2</name>
            <protectionLevel>3</protectionLevel>
            <acceptableUnit>mm</acceptableUnit>
            <moveableName>hfmx2_positioner</moveableName>
        </EpicsAxisLinearDOF>
        <EpicsAxisLinearDOF>
            <local>true</local>
            <name>hfmy1</name>
            <protectionLevel>3</protectionLevel>
            <acceptableUnit>mm</acceptableUnit>
            <moveableName>hfmy1_positioner</moveableName>
        </EpicsAxisLinearDOF>
        <EpicsAxisLinearDOF>
            <local>true</local>
            <name>hfmy2</name>
            <protectionLevel>3</protectionLevel>
            <acceptableUnit>mm</acceptableUnit>
            <moveableName>hfmy2_positioner</moveableName>
        </EpicsAxisLinearDOF>
        <EpicsAxisLinearDOF>
            <local>true</local>
            <name>hfmy3</name>
            <protectionLevel>3</protectionLevel>
            <acceptableUnit>mm</acceptableUnit>
            <moveableName>hfmy3_positioner</moveableName>
        </EpicsAxisLinearDOF>       
        
        <EpicsAxisLinearDOF>
            <local>true</local>
            <name>vfmtip</name>
            <protectionLevel>3</protectionLevel>
            <acceptableUnit>mm</acceptableUnit>
            <moveableName>vfmtip_positioner</moveableName>
        </EpicsAxisLinearDOF>
        <EpicsAxisLinearDOF>
            <local>true</local>
            <name>vfmy2y3</name>
            <protectionLevel>3</protectionLevel>
            <acceptableUnit>mm</acceptableUnit>
            <moveableName>vfmy2y3_positioner</moveableName>
        </EpicsAxisLinearDOF> 
    </GenericOE>
    
    <!-- Tertiary Slits / S3 Optical Element -->
    <GenericOE>
        <name>S3</name>
            <local>true</local>
        <LinearPositioner>
            <local>true</local>
            <name>s3xpos_positioner</name>
            <motorName>s3xpos_motor</motorName>
            <stepsPerUnit>1</stepsPerUnit>
            <softLimitLow>-100</softLimitLow>
            <softLimitHigh>100</softLimitHigh>
            <poll>false</poll>
        </LinearPositioner>
        <LinearPositioner>
            <local>true</local>
            <name>s3xgap_positioner</name>
            <motorName>s3xgap_motor</motorName>
            <stepsPerUnit>1</stepsPerUnit>
            <softLimitLow>-100</softLimitLow>
            <softLimitHigh>100</softLimitHigh>
            <poll>false</poll>
        </LinearPositioner>
        <LinearPositioner>
            <local>true</local>
            <name>s3ypos_positioner</name>
            <motorName>s3ypos_motor</motorName>
            <stepsPerUnit>1</stepsPerUnit>
            <softLimitLow>-100</softLimitLow>
            <softLimitHigh>100</softLimitHigh>
            <poll>false</poll>
        </LinearPositioner>
        <LinearPositioner>
            <local>true</local>
            <name>s3ygap_positioner</name>
            <motorName>s3ygap_motor</motorName>
            <stepsPerUnit>1</stepsPerUnit>
            <softLimitLow>-100</softLimitLow>
            <softLimitHigh>100</softLimitHigh>
            <poll>false</poll>
        </LinearPositioner>
        <LinearPositioner>
            <local>true</local>
            <name>s3xplus_positioner</name>
            <motorName>s3xplus_motor</motorName>
            <stepsPerUnit>1</stepsPerUnit>
            <softLimitLow>-100</softLimitLow>
            <softLimitHigh>100</softLimitHigh>
            <poll>false</poll>
        </LinearPositioner>
        <LinearPositioner>
            <local>true</local>
            <name>s3xminus_positioner</name>
            <motorName>s3xminus_motor</motorName>
            <stepsPerUnit>1</stepsPerUnit>
            <softLimitLow>-100</softLimitLow>
            <softLimitHigh>100</softLimitHigh>
            <poll>false</poll>
        </LinearPositioner>
        <LinearPositioner>
            <local>true</local>
            <name>s3yplus_positioner</name>
            <motorName>s3yplus_motor</motorName>
            <stepsPerUnit>1</stepsPerUnit>
            <softLimitLow>-100</softLimitLow>
            <softLimitHigh>100</softLimitHigh>
            <poll>false</poll>
        </LinearPositioner>
        <LinearPositioner>
            <local>true</local>
            <name>s3yminus_positioner</name>
            <motorName>s3yminus_motor</motorName>
            <stepsPerUnit>1</stepsPerUnit>
            <softLimitLow>-100</softLimitLow>
            <softLimitHigh>100</softLimitHigh>
            <poll>false</poll>
        </LinearPositioner>
        
        <EpicsAxisLinearDOF>
            <local>true</local>
            <name>s3xcentre</name>
            <protectionLevel>2</protectionLevel>
            <acceptableUnit>mm</acceptableUnit>
            <moveableName>s3xpos_positioner</moveableName>
        </EpicsAxisLinearDOF>
        <EpicsAxisLinearDOF>
            <local>true</local>
            <name>s3xgap</name>
            <protectionLevel>2</protectionLevel>
            <acceptableUnit>mm</acceptableUnit>
            <moveableName>s3xgap_positioner</moveableName>
        </EpicsAxisLinearDOF>
        <EpicsAxisLinearDOF>
            <local>true</local>
            <name>s3ycentre</name>
            <protectionLevel>2</protectionLevel>
            <acceptableUnit>mm</acceptableUnit>
            <moveableName>s3ypos_positioner</moveableName>
        </EpicsAxisLinearDOF>
        <EpicsAxisLinearDOF>
            <local>true</local>
            <name>s3ygap</name>
            <protectionLevel>2</protectionLevel>
            <acceptableUnit>mm</acceptableUnit>
            <moveableName>s3ygap_positioner</moveableName>
        </EpicsAxisLinearDOF>
        <EpicsAxisLinearDOF>
            <local>true</local>
            <name>s3xplus</name>
            <protectionLevel>2</protectionLevel>
            <acceptableUnit>mm</acceptableUnit>
            <moveableName>s3xplus_positioner</moveableName>
        </EpicsAxisLinearDOF>
        <EpicsAxisLinearDOF>
            <local>true</local>
            <name>s3xminus</name>
            <protectionLevel>2</protectionLevel>
            <acceptableUnit>mm</acceptableUnit>
            <moveableName>s3xminus_positioner</moveableName>
        </EpicsAxisLinearDOF>
        <EpicsAxisLinearDOF>
            <local>true</local>
            <name>s3yplus</name>
            <protectionLevel>2</protectionLevel>
            <acceptableUnit>mm</acceptableUnit>
            <moveableName>s3yplus_positioner</moveableName>
        </EpicsAxisLinearDOF>
        <EpicsAxisLinearDOF>
            <local>true</local>
            <name>s3yminus</name>
            <protectionLevel>2</protectionLevel>
            <acceptableUnit>mm</acceptableUnit>
            <moveableName>s3yminus_positioner</moveableName>
        </EpicsAxisLinearDOF>
    </GenericOE>     
    <!-- D4 -->
    <GenericOE>
        <name>D4</name>
            <local>true</local>
        <LinearPositioner>
            <local>true</local>
            <name>d4motor_positioner</name>
            <motorName>d4motor_motor</motorName>
            <stepsPerUnit>1</stepsPerUnit>
            <softLimitLow>-100</softLimitLow>
            <softLimitHigh>100</softLimitHigh>
            <poll>false</poll>
        </LinearPositioner>
        <EpicsAxisLinearDOF>
            <local>true</local>
            <name>d4motor</name>
            <protectionLevel>0</protectionLevel>
            <acceptableUnit>mm</acceptableUnit>
            <moveableName>d4motor_positioner</moveableName>
        </EpicsAxisLinearDOF>
    </GenericOE>   
    <!-- D5 -->
    <GenericOE>
        <name>D5</name>
            <local>true</local>
        <LinearPositioner>
            <local>true</local>
            <name>d5motor_positioner</name>
            <motorName>d5motor_motor</motorName>
            <stepsPerUnit>1</stepsPerUnit>
            <softLimitLow>-100</softLimitLow>
            <softLimitHigh>100</softLimitHigh>
            <poll>false</poll>
        </LinearPositioner>
        <EpicsAxisLinearDOF>
            <local>true</local>
            <name>d5motor</name>
            <protectionLevel>0</protectionLevel>
            <acceptableUnit>mm</acceptableUnit>
            <moveableName>d5motor_positioner</moveableName>
        </EpicsAxisLinearDOF>
    </GenericOE>   
    <!-- D6 -->
    <GenericOE>
        <name>D6</name>
            <local>true</local>
        <LinearPositioner>
            <local>true</local>
            <name>d6motor_positioner</name>
            <motorName>d6motor_motor</motorName>
            <stepsPerUnit>1</stepsPerUnit>
            <softLimitLow>-100</softLimitLow>
            <softLimitHigh>100</softLimitHigh>
            <poll>false</poll>
        </LinearPositioner>
        <EpicsAxisLinearDOF>
            <local>true</local>
            <name>d6motor</name>
            <protectionLevel>0</protectionLevel>
            <acceptableUnit>mm</acceptableUnit>
            <moveableName>d6motor_positioner</moveableName>
        </EpicsAxisLinearDOF>
    </GenericOE>   
    <!-- 4th Slits / S4 Optical Element -->
    <GenericOE>
        <name>S4</name>
            <local>true</local>
        <LinearPositioner>
            <local>true</local>
            <name>s4xpos_positioner</name>
            <motorName>s4xpos_motor</motorName>
            <stepsPerUnit>1</stepsPerUnit>
            <softLimitLow>-100</softLimitLow>
            <softLimitHigh>100</softLimitHigh>
            <poll>false</poll>
        </LinearPositioner>
        <LinearPositioner>
            <local>true</local>
            <name>s4xgap_positioner</name>
            <motorName>s4xgap_motor</motorName>
            <stepsPerUnit>1</stepsPerUnit>
            <softLimitLow>-100</softLimitLow>
            <softLimitHigh>100</softLimitHigh>
            <poll>false</poll>
        </LinearPositioner>
        <LinearPositioner>
            <local>true</local>
            <name>s4ypos_positioner</name>
            <motorName>s4ypos_motor</motorName>
            <stepsPerUnit>1</stepsPerUnit>
            <softLimitLow>-100</softLimitLow>
            <softLimitHigh>100</softLimitHigh>
            <poll>false</poll>
        </LinearPositioner>
        <LinearPositioner>
            <local>true</local>
            <name>s4ygap_positioner</name>
            <motorName>s4ygap_motor</motorName>
            <stepsPerUnit>1</stepsPerUnit>
            <softLimitLow>-100</softLimitLow>
            <softLimitHigh>100</softLimitHigh>
            <poll>false</poll>
        </LinearPositioner>
        <LinearPositioner>
            <local>true</local>
            <name>s4xplus_positioner</name>
            <motorName>s4xplus_motor</motorName>
            <stepsPerUnit>1</stepsPerUnit>
            <softLimitLow>-100</softLimitLow>
            <softLimitHigh>100</softLimitHigh>
            <poll>false</poll>
        </LinearPositioner>
        <LinearPositioner>
            <local>true</local>
            <name>s4xminus_positioner</name>
            <motorName>s4xminus_motor</motorName>
            <stepsPerUnit>1</stepsPerUnit>
            <softLimitLow>-100</softLimitLow>
            <softLimitHigh>100</softLimitHigh>
            <poll>false</poll>
        </LinearPositioner>
        <LinearPositioner>
            <local>true</local>
            <name>s4yplus_positioner</name>
            <motorName>s4yplus_motor</motorName>
            <stepsPerUnit>1</stepsPerUnit>
            <softLimitLow>-100</softLimitLow>
            <softLimitHigh>100</softLimitHigh>
            <poll>false</poll>
        </LinearPositioner>
        <LinearPositioner>
            <local>true</local>
            <name>s4yminus_positioner</name>
            <motorName>s4yminus_motor</motorName>
            <stepsPerUnit>1</stepsPerUnit>
            <softLimitLow>-100</softLimitLow>
            <softLimitHigh>100</softLimitHigh>
            <poll>false</poll>
        </LinearPositioner>
        
        <EpicsAxisLinearDOF>
            <local>true</local>
            <name>s4xcentre</name>
            <protectionLevel>2</protectionLevel>
            <acceptableUnit>mm</acceptableUnit>
            <moveableName>s4xpos_positioner</moveableName>
        </EpicsAxisLinearDOF>
        <EpicsAxisLinearDOF>
            <local>true</local>
            <name>s4xgap</name>
            <protectionLevel>2</protectionLevel>
            <acceptableUnit>mm</acceptableUnit>
            <moveableName>s4xgap_positioner</moveableName>
        </EpicsAxisLinearDOF>
        <EpicsAxisLinearDOF>
            <local>true</local>
            <name>s4ycentre</name>
            <protectionLevel>2</protectionLevel>
            <acceptableUnit>mm</acceptableUnit>
            <moveableName>s4ypos_positioner</moveableName>
        </EpicsAxisLinearDOF>
        <EpicsAxisLinearDOF>
            <local>true</local>
            <name>s4ygap</name>
            <protectionLevel>2</protectionLevel>
            <acceptableUnit>mm</acceptableUnit>
            <moveableName>s4ygap_positioner</moveableName>
        </EpicsAxisLinearDOF>
        <EpicsAxisLinearDOF>
            <local>true</local>
            <name>s4xplus</name>
            <protectionLevel>2</protectionLevel>
            <acceptableUnit>mm</acceptableUnit>
            <moveableName>s4xplus_positioner</moveableName>
        </EpicsAxisLinearDOF>
        <EpicsAxisLinearDOF>
            <local>true</local>
            <name>s4xminus</name>
            <protectionLevel>2</protectionLevel>
            <acceptableUnit>mm</acceptableUnit>
            <moveableName>s4xminus_positioner</moveableName>
        </EpicsAxisLinearDOF>
        <EpicsAxisLinearDOF>
            <local>true</local>
            <name>s4yplus</name>
            <protectionLevel>2</protectionLevel>
            <acceptableUnit>mm</acceptableUnit>
            <moveableName>s4yplus_positioner</moveableName>
        </EpicsAxisLinearDOF>
        <EpicsAxisLinearDOF>
            <local>true</local>
            <name>s4yminus</name>
            <protectionLevel>2</protectionLevel>
            <acceptableUnit>mm</acceptableUnit>
            <moveableName>s4yminus_positioner</moveableName>
        </EpicsAxisLinearDOF>
    </GenericOE>

    <!-- 5th Slits / S5S (SAXS) Optical Element -->
    <!-- user visible stuff renamed to S5 following Nick's suggestion -->
    <GenericOE>
        <name>S5</name>
            <local>true</local>
        <LinearPositioner>
            <local>true</local>
            <name>s5sxpos_positioner</name>
            <motorName>s5sxpos_motor</motorName>
            <stepsPerUnit>1</stepsPerUnit>
            <softLimitLow>-100</softLimitLow>
            <softLimitHigh>100</softLimitHigh>
            <poll>false</poll>
        </LinearPositioner>
        <LinearPositioner>
            <local>true</local>
            <name>s5sxgap_positioner</name>
            <motorName>s5sxgap_motor</motorName>
            <stepsPerUnit>1</stepsPerUnit>
            <softLimitLow>-100</softLimitLow>
            <softLimitHigh>100</softLimitHigh>
            <poll>false</poll>
        </LinearPositioner>
        <LinearPositioner>
            <local>true</local>
            <name>s5sypos_positioner</name>
            <motorName>s5sypos_motor</motorName>
            <stepsPerUnit>1</stepsPerUnit>
            <softLimitLow>-100</softLimitLow>
            <softLimitHigh>100</softLimitHigh>
            <poll>false</poll>
        </LinearPositioner>
        <LinearPositioner>
            <local>true</local>
            <name>s5sygap_positioner</name>
            <motorName>s5sygap_motor</motorName>
            <stepsPerUnit>1</stepsPerUnit>
            <softLimitLow>-100</softLimitLow>
            <softLimitHigh>100</softLimitHigh>
            <poll>false</poll>
        </LinearPositioner>
        <LinearPositioner>
            <local>true</local>
            <name>s5sxplus_positioner</name>
            <motorName>s5sxplus_motor</motorName>
            <stepsPerUnit>1</stepsPerUnit>
            <softLimitLow>-100</softLimitLow>
            <softLimitHigh>100</softLimitHigh>
            <poll>false</poll>
        </LinearPositioner>
        <LinearPositioner>
            <local>true</local>
            <name>s5sxminus_positioner</name>
            <motorName>s5sxminus_motor</motorName>
            <stepsPerUnit>1</stepsPerUnit>
            <softLimitLow>-100</softLimitLow>
            <softLimitHigh>100</softLimitHigh>
            <poll>false</poll>
        </LinearPositioner>
        <LinearPositioner>
            <local>true</local>
            <name>s5syplus_positioner</name>
            <motorName>s5syplus_motor</motorName>
            <stepsPerUnit>1</stepsPerUnit>
            <softLimitLow>-100</softLimitLow>
            <softLimitHigh>100</softLimitHigh>
            <poll>false</poll>
        </LinearPositioner>
        <LinearPositioner>
            <local>true</local>
            <name>s5syminus_positioner</name>
            <motorName>s5syminus_motor</motorName>
            <stepsPerUnit>1</stepsPerUnit>
            <softLimitLow>-100</softLimitLow>
            <softLimitHigh>100</softLimitHigh>
            <poll>false</poll>
        </LinearPositioner>
        
        <EpicsAxisLinearDOF>
            <local>true</local>
            <name>s5xcentre</name>
            <protectionLevel>2</protectionLevel>
            <acceptableUnit>mm</acceptableUnit>
            <moveableName>s5sxpos_positioner</moveableName>
        </EpicsAxisLinearDOF>
        <EpicsAxisLinearDOF>
            <local>true</local>
            <name>s5xgap</name>
            <protectionLevel>2</protectionLevel>
            <acceptableUnit>mm</acceptableUnit>
            <moveableName>s5sxgap_positioner</moveableName>
        </EpicsAxisLinearDOF>
        <EpicsAxisLinearDOF>
            <local>true</local>
            <name>s5ycentre</name>
            <protectionLevel>2</protectionLevel>
            <acceptableUnit>mm</acceptableUnit>
            <moveableName>s5sypos_positioner</moveableName>
        </EpicsAxisLinearDOF>
        <EpicsAxisLinearDOF>
            <local>true</local>
            <name>s5ygap</name>
            <protectionLevel>2</protectionLevel>
            <acceptableUnit>mm</acceptableUnit>
            <moveableName>s5sygap_positioner</moveableName>
        </EpicsAxisLinearDOF>
        <EpicsAxisLinearDOF>
            <local>true</local>
            <name>s5xplus</name>
            <protectionLevel>2</protectionLevel>
            <acceptableUnit>mm</acceptableUnit>
            <moveableName>s5sxplus_positioner</moveableName>
        </EpicsAxisLinearDOF>
        <EpicsAxisLinearDOF>
            <local>true</local>
            <name>s5xminus</name>
            <protectionLevel>2</protectionLevel>
            <acceptableUnit>mm</acceptableUnit>
            <moveableName>s5sxminus_positioner</moveableName>
        </EpicsAxisLinearDOF>
        <EpicsAxisLinearDOF>
            <local>true</local>
            <name>s5yplus</name>
            <protectionLevel>2</protectionLevel>
            <acceptableUnit>mm</acceptableUnit>
            <moveableName>s5syplus_positioner</moveableName>
        </EpicsAxisLinearDOF>
        <EpicsAxisLinearDOF>
            <local>true</local>
            <name>s5yminus</name>
            <protectionLevel>2</protectionLevel>
            <acceptableUnit>mm</acceptableUnit>
            <moveableName>s5syminus_positioner</moveableName>
        </EpicsAxisLinearDOF>
    </GenericOE>

    <!-- D7 -->
    <GenericOE>
        <name>D7</name>
            <local>true</local>
        <LinearPositioner>
            <local>true</local>
            <name>d7motor_positioner</name>
            <motorName>d7motor_motor</motorName>
            <stepsPerUnit>1</stepsPerUnit>
            <softLimitLow>-100</softLimitLow>
            <softLimitHigh>100</softLimitHigh>
            <poll>false</poll>
        </LinearPositioner>
        <EpicsAxisLinearDOF>
            <local>true</local>
            <name>d7motor</name>
            <protectionLevel>0</protectionLevel>
            <acceptableUnit>mm</acceptableUnit>
            <moveableName>d7motor_positioner</moveableName>
        </EpicsAxisLinearDOF>
    </GenericOE>   
    <!-- BCO Optical Element - used to be T4 -->
    <GenericOE>
        <name>BCO</name>
            <local>true</local>
        <LinearPositioner>
            <local>true</local>
            <name>bcox_positioner</name>
            <motorName>bcox_motor</motorName>
            <stepsPerUnit>1</stepsPerUnit>
            <softLimitLow>-100</softLimitLow>
            <softLimitHigh>100</softLimitHigh>
            <poll>false</poll>
        </LinearPositioner>
        <LinearPositioner>
            <local>true</local>
            <name>bcoy_positioner</name>
            <motorName>bcoy_motor</motorName>
            <stepsPerUnit>1</stepsPerUnit>
            <softLimitLow>-100</softLimitLow>
            <softLimitHigh>100</softLimitHigh>
            <poll>false</poll>
        </LinearPositioner>
        <AngularPositioner>
            <local>true</local>
            <name>bcopitch_positioner</name>
            <motorName>bcopitch_motor</motorName>
            <stepsPerUnit>1</stepsPerUnit>
            <softLimitLow>-100</softLimitLow>
            <softLimitHigh>100</softLimitHigh>
            <poll>false</poll>
        </AngularPositioner>
        
        <EpicsAxisLinearDOF>
            <local>true</local>
            <name>bcox</name>
            <protectionLevel>3</protectionLevel>
            <acceptableUnit>mm</acceptableUnit>
            <moveableName>bcox_positioner</moveableName>
        </EpicsAxisLinearDOF>
        <EpicsAxisLinearDOF>
            <local>true</local>
            <name>bcoy</name>
            <protectionLevel>3</protectionLevel>
            <acceptableUnit>mm</acceptableUnit>
            <moveableName>bcoy_positioner</moveableName>
        </EpicsAxisLinearDOF>
        <EpicsAxisAngularDOF>
            <local>true</local>
            <name>bcopitch</name>
            <protectionLevel>3</protectionLevel>
            <acceptableUnit>Deg</acceptableUnit>
            <moveableName>bcopitch_positioner</moveableName>
        </EpicsAxisAngularDOF>
    </GenericOE> 
    
    <!-- PXY Optical Element  -->
    <GenericOE>
        <name>PXY</name>
            <local>true</local>
        <LinearPositioner>
            <local>true</local>
            <name>pxyx_positioner</name>
            <motorName>pxyx_motor</motorName>
            <stepsPerUnit>1</stepsPerUnit>
            <softLimitLow>-100</softLimitLow>
            <softLimitHigh>100</softLimitHigh>
            <poll>false</poll>
        </LinearPositioner>
        <LinearPositioner>
            <local>true</local>
            <name>pxyy_positioner</name>
            <motorName>pxyy_motor</motorName>
            <stepsPerUnit>1</stepsPerUnit>
            <softLimitLow>-100</softLimitLow>
            <softLimitHigh>100</softLimitHigh>
            <poll>false</poll>
        </LinearPositioner>

        <EpicsAxisLinearDOF>
            <local>true</local>
            <name>pxyx</name>
            <protectionLevel>0</protectionLevel>
            <acceptableUnit>mm</acceptableUnit>
            <moveableName>pxyx_positioner</moveableName>
        </EpicsAxisLinearDOF>
        <EpicsAxisLinearDOF>
            <local>true</local>
            <name>pxyy</name>
            <protectionLevel>0</protectionLevel>
            <acceptableUnit>mm</acceptableUnit>
            <moveableName>pxyy_positioner</moveableName>
        </EpicsAxisLinearDOF>
    </GenericOE>

    <!-- ROT Optical Element  -->
    <GenericOE>
        <name>ROT</name>
            <local>true</local>
        <AngularPositioner>
            <local>true</local>
            <name>rot_positioner</name>
            <motorName>rot_motor</motorName>
            <stepsPerUnit>1</stepsPerUnit>
            <softLimitLow>-100</softLimitLow>
            <softLimitHigh>100</softLimitHigh>
            <poll>false</poll>
        </AngularPositioner>
        <EpicsAxisAngularDOF>
            <local>true</local>
            <name>rot</name>
            <protectionLevel>0</protectionLevel>
            <acceptableUnit>Deg</acceptableUnit>
            <moveableName>rot_positioner</moveableName>
        </EpicsAxisAngularDOF>
    </GenericOE>

    
    <!--SAX sample Table Base Optical Element - used to be T1 -->
    <GenericOE>
        <name>BASE</name>
            <local>true</local>
        <LinearPositioner>
            <local>true</local>
            <name>t1x_positioner</name>
            <motorName>t1x_motor</motorName>
            <stepsPerUnit>1</stepsPerUnit>
            <softLimitLow>-100</softLimitLow>
            <softLimitHigh>100</softLimitHigh>
            <poll>false</poll>
        </LinearPositioner>
        <LinearPositioner>
            <local>true</local>
            <name>t1y_positioner</name>
            <motorName>t1y_motor</motorName>
            <stepsPerUnit>1</stepsPerUnit>
            <softLimitLow>-100</softLimitLow>
            <softLimitHigh>100</softLimitHigh>
            <poll>false</poll>
        </LinearPositioner>
        <AngularPositioner>
            <local>true</local>
            <name>t1pitch_positioner</name>
            <motorName>t1pitch_motor</motorName>
            <stepsPerUnit>1</stepsPerUnit>
            <softLimitLow>-100</softLimitLow>
            <softLimitHigh>100</softLimitHigh>
            <poll>false</poll>
        </AngularPositioner>
        <AngularPositioner>
            <local>true</local>
            <name>t1yaw_positioner</name>
            <motorName>t1yaw_motor</motorName>
            <stepsPerUnit>1</stepsPerUnit>
            <softLimitLow>-100</softLimitLow>
            <softLimitHigh>100</softLimitHigh>
            <poll>false</poll>
        </AngularPositioner>
        
        <!-- TODO downgrade protection heighened for testing -->
        <EpicsAxisLinearDOF>
            <local>true</local>
            <name>basex</name>
            <protectionLevel>0</protectionLevel>
            <acceptableUnit>mm</acceptableUnit>
            <moveableName>t1x_positioner</moveableName>
        </EpicsAxisLinearDOF>
        <EpicsAxisLinearDOF>
            <local>true</local>
            <name>basey</name>
            <protectionLevel>0</protectionLevel>
            <acceptableUnit>mm</acceptableUnit>
            <moveableName>t1y_positioner</moveableName>
        </EpicsAxisLinearDOF>
        <EpicsAxisAngularDOF>
            <local>true</local>
            <name>basepitch</name>
            <protectionLevel>0</protectionLevel>
            <acceptableUnit>Deg</acceptableUnit>
            <moveableName>t1pitch_positioner</moveableName>
        </EpicsAxisAngularDOF>
        <EpicsAxisAngularDOF>
            <local>true</local>
            <name>baseyaw</name>
            <protectionLevel>0</protectionLevel>
            <acceptableUnit>Deg</acceptableUnit>
            <moveableName>t1yaw_positioner</moveableName>
        </EpicsAxisAngularDOF>
    </GenericOE> 
    
    <!--WAX Detector Optical Element -->
    <GenericOE>
        <name>WAX</name>
            <local>true</local>
        <LinearPositioner>
            <local>true</local>
            <name>wdx_positioner</name>
            <motorName>wdx_motor</motorName>
            <stepsPerUnit>1</stepsPerUnit>
            <softLimitLow>-100</softLimitLow>
            <softLimitHigh>100</softLimitHigh>
            <poll>false</poll>
        </LinearPositioner>
        <LinearPositioner>
            <local>true</local>
            <name>wdy_positioner</name>
            <motorName>wdy_motor</motorName>
            <stepsPerUnit>1</stepsPerUnit>
            <softLimitLow>-100</softLimitLow>
            <softLimitHigh>100</softLimitHigh>
            <poll>false</poll>
        </LinearPositioner>
        
        <EpicsAxisLinearDOF>
            <local>true</local>
            <name>wdx</name>
            <protectionLevel>2</protectionLevel>
            <acceptableUnit>mm</acceptableUnit>
            <moveableName>wdx_positioner</moveableName>
        </EpicsAxisLinearDOF>
        <EpicsAxisLinearDOF>
            <local>true</local>
            <name>wdy</name>
            <protectionLevel>2</protectionLevel>
            <acceptableUnit>mm</acceptableUnit>
            <moveableName>wdy_positioner</moveableName>
        </EpicsAxisLinearDOF>
    </GenericOE> 
    <!--SAX Detector Motion SAX Optical Element -->
    <GenericOE>
        <name>SAX</name>
            <local>true</local>
        <LinearPositioner>
            <local>true</local>
            <name>sdx_positioner</name>
            <motorName>sdx_motor</motorName>
            <stepsPerUnit>1</stepsPerUnit>
            <softLimitLow>-100</softLimitLow>
            <softLimitHigh>100</softLimitHigh>
            <poll>false</poll>
        </LinearPositioner>
        <LinearPositioner>
            <local>true</local>
            <name>sdy_positioner</name>
            <motorName>sdy_motor</motorName>
            <stepsPerUnit>1</stepsPerUnit>
            <softLimitLow>-100</softLimitLow>
            <softLimitHigh>100</softLimitHigh>
            <poll>false</poll>
        </LinearPositioner>
        <AngularPositioner>
            <local>true</local>
            <name>sdhpitch_positioner</name>
            <motorName>sdhpitch_motor</motorName>
            <stepsPerUnit>1</stepsPerUnit>
            <softLimitLow>-100</softLimitLow>
            <softLimitHigh>100</softLimitHigh>
            <poll>false</poll>
        </AngularPositioner>
        <AngularPositioner>
            <local>true</local>
            <name>sdrpitch_positioner</name>
            <motorName>sdrpitch_motor</motorName>
            <stepsPerUnit>1</stepsPerUnit>
            <softLimitLow>-100</softLimitLow>
            <softLimitHigh>100</softLimitHigh>
            <poll>false</poll>
        </AngularPositioner>
        
        <EpicsAxisLinearDOF>
            <local>true</local>
            <name>sdx</name>
            <protectionLevel>2</protectionLevel>
            <acceptableUnit>mm</acceptableUnit>
            <moveableName>sdx_positioner</moveableName>
        </EpicsAxisLinearDOF>
        <EpicsAxisLinearDOF>
            <local>true</local>
            <name>sdy</name>
            <protectionLevel>2</protectionLevel>
            <acceptableUnit>mm</acceptableUnit>
            <moveableName>sdy_positioner</moveableName>
        </EpicsAxisLinearDOF>
        <EpicsAxisAngularDOF>
            <local>true</local>
            <name>sdhpitch</name>
            <protectionLevel>2</protectionLevel>
            <acceptableUnit>Deg</acceptableUnit>
            <moveableName>sdhpitch_positioner</moveableName>
        </EpicsAxisAngularDOF>
        <EpicsAxisAngularDOF>
            <local>true</local>
            <name>sdrpitch</name>
            <protectionLevel>2</protectionLevel>
            <acceptableUnit>Deg</acceptableUnit>
            <moveableName>sdrpitch_positioner</moveableName>
        </EpicsAxisAngularDOF>
    </GenericOE> 
    <!--SAX Detector Motion SAX Optical Element -->
    <GenericOE>
        <name>SBS</name>
            <local>true</local>
        <LinearPositioner>
            <local>true</local>
            <name>sbsx_positioner</name>
            <motorName>sbsx_motor</motorName>
            <stepsPerUnit>1</stepsPerUnit>
            <softLimitLow>-100</softLimitLow>
            <softLimitHigh>100</softLimitHigh>
            <poll>false</poll>
        </LinearPositioner>
        <LinearPositioner>
            <local>true</local>
            <name>sbsy_positioner</name>
            <motorName>sbsy_motor</motorName>
            <stepsPerUnit>1</stepsPerUnit>
            <softLimitLow>-100</softLimitLow>
            <softLimitHigh>100</softLimitHigh>
            <poll>false</poll>
        </LinearPositioner>
            
        <EpicsAxisLinearDOF>
            <local>true</local>
            <name>sbsx</name>
            <protectionLevel>2</protectionLevel>
            <acceptableUnit>mm</acceptableUnit>
            <moveableName>sbsx_positioner</moveableName>
        </EpicsAxisLinearDOF>
        <EpicsAxisLinearDOF>
            <local>true</local>
            <name>sbsy</name>
            <protectionLevel>2</protectionLevel>
            <acceptableUnit>mm</acceptableUnit>
            <moveableName>sbsy_positioner</moveableName>
        </EpicsAxisLinearDOF>
        
    </GenericOE> 
                                
    <!-- User Motors -->
    <GenericOE>
        <name>PDL</name>
        <LinearPositioner>
            <local>true</local>
            <name>usermotor1_positioner</name>
            <motorName>usermotor1_motor</motorName>
            <stepsPerUnit>1</stepsPerUnit>
            <softLimitLow>-100</softLimitLow>
            <softLimitHigh>100</softLimitHigh>
            <poll>false</poll>
        </LinearPositioner>
        <LinearPositioner>
            <local>true</local>
            <name>usermotor2_positioner</name>
            <motorName>usermotor2_motor</motorName>
            <stepsPerUnit>1</stepsPerUnit>
            <softLimitLow>-100</softLimitLow>
            <softLimitHigh>100</softLimitHigh>
            <poll>false</poll>
        </LinearPositioner>
        <LinearPositioner>
            <local>true</local>
            <name>usermotor3_positioner</name>
            <motorName>usermotor3_motor</motorName>
            <stepsPerUnit>1</stepsPerUnit>
            <softLimitLow>-100</softLimitLow>
            <softLimitHigh>100</softLimitHigh>
            <poll>false</poll>
        </LinearPositioner>

        <EpicsAxisLinearDOF>
            <local>true</local>
            <name>xusermotor1</name>
            <protectionLevel>0</protectionLevel>
            <acceptableUnit>mm</acceptableUnit>
            <moveableName>usermotor1_positioner</moveableName>
        </EpicsAxisLinearDOF>
        <EpicsAxisLinearDOF>
            <local>true</local>
            <name>yusermotor2</name>
            <protectionLevel>0</protectionLevel>
            <acceptableUnit>mm</acceptableUnit>
            <moveableName>usermotor2_positioner</moveableName>
        </EpicsAxisLinearDOF>
        <EpicsAxisLinearDOF>
            <local>true</local>
            <name>zusermotor3</name>
            <protectionLevel>0</protectionLevel>
            <acceptableUnit>mm</acceptableUnit>
            <moveableName>usermotor3_positioner</moveableName>
        </EpicsAxisLinearDOF>
            <local>true</local>
    </GenericOE>

    <GenericOE>
        <name>USER</name>
            <local>true</local>
        <LinearPositioner>
            <local>true</local>
            <name>usermotor4_positioner</name>
            <motorName>usermotor4_motor</motorName>
            <stepsPerUnit>1</stepsPerUnit>
            <softLimitLow>-100</softLimitLow>
            <softLimitHigh>100</softLimitHigh>
            <poll>false</poll>
        </LinearPositioner>

        <EpicsAxisLinearDOF>
            <local>true</local>
            <name>usermotor4</name>
            <protectionLevel>0</protectionLevel>
            <acceptableUnit>mm</acceptableUnit>
            <moveableName>usermotor4_positioner</moveableName>
        </EpicsAxisLinearDOF>
    </GenericOE>

</ObjectFactory>
