<?xml version="1.0" encoding="UTF-8"?>
<beans xmlns="http://www.springframework.org/schema/beans"
	xmlns:xsi="http://www.w3.org/2001/XMLSchema-instance"
	xsi:schemaLocation="http://www.springframework.org/schema/beans http://www.springframework.org/schema/beans/spring-beans-3.0.xsd">
	
	<bean id="ls2x" class="gda.device.scannable.ScannableMotor">
		<property name="motor" ref="lsx_motor"/>
	</bean>
	<bean id="ls2y" class="gda.device.scannable.ScannableMotor">
		<property name="motor" ref="ls2y1_motor"/>
	</bean>
	<bean id="ls2rot" class="gda.device.scannable.ScannableMotor">
		<property name="motor" ref="ls2yrot_motor"/>
	</bean>
	<bean id="ls2xtop" class="gda.device.scannable.ScannableMotor">
		<property name="motor" ref="ls2x_motor"/>
	</bean>
	<bean id="ls2ytop" class="gda.device.scannable.ScannableMotor">
		<property name="motor" ref="ls2y2_motor"/>
	</bean>
	<bean id="ls2ztop" class="gda.device.scannable.ScannableMotor">
		<property name="motor" ref="ls2z_motor"/>
	</bean>
	<bean id="ls2roll" class="gda.device.scannable.ScannableMotor">
		<property name="motor" ref="ls2roll_motor"/>
	</bean>
	<bean id="ls2pitch" class="gda.device.scannable.ScannableMotor">
		<property name="motor" ref="ls2pitch_motor"/>
	</bean>
	
	<bean id="ls2" class="org.opengda.lde.experiments.SampleStage">
		<property name="groupMembers">
			<list>
				<ref bean="ls2x"/>
				<ref bean="ls2y"/>
				<ref bean="ls2rot"/>
				<ref bean="ls2xtop"/>
				<ref bean="ls2ytop"/>
				<ref bean="ls2ztop"/>
				<ref bean="ls2roll"/>
				<ref bean="ls2pitch"/>
			</list>
		</property>
		<property name="engagePosition" value="0.0"/>
		<property name="parkPosition" value="-400.0"/>
		<property name="positionTolerance" value="0.001"/>
		<property name="zPosition" value="-400.0"/>
	</bean>
</beans>
